[
  {
    "_id": "62acaf71de6bdc0b5eacc542",
    "name": "leão",
    "reino": "animalia",
    "filo": "chordata",
    "classe": "mammalia",
    "infraclasse": "plancetália",
    "ordem": "carnivora",
    "familia": "felidae",
    "genero": "Panthera",
    "especie": "P. leo",
    "__v": 0
  },
  {
    "_id": "62acb07c6c82336ee37c6210",
    "name": "tigre",
    "reino": "animalia",
    "filo": "chordata",
    "classe": "mammalia",
    "infraclasse": "plancetália",
    "ordem": "carnivora",
    "familia": "felidae",
    "genero": "Panthera",
    "especie": "P. tigris",
    "__v": 0
  }
]